MANIFEST.in
README.rst
setup.py
docs/HISTORY.txt
docs/LICENSE.txt
src/collective/__init__.py
src/collective.cmissearch.egg-info/PKG-INFO
src/collective.cmissearch.egg-info/SOURCES.txt
src/collective.cmissearch.egg-info/dependency_links.txt
src/collective.cmissearch.egg-info/namespace_packages.txt
src/collective.cmissearch.egg-info/not-zip-safe
src/collective.cmissearch.egg-info/requires.txt
src/collective.cmissearch.egg-info/top_level.txt
src/collective/cmissearch/__init__.py
src/collective/cmissearch/cmis.py
src/collective/cmissearch/configure.zcml
src/collective/cmissearch/default.py
src/collective/cmissearch/interfaces.py
src/collective/cmissearch/portlets.py
src/collective/cmissearch/search.py
src/collective/cmissearch/i18n/collective.cmissearch.pot
src/collective/cmissearch/i18n/en/LC_MESSAGES/collective.cmissearch.mo
src/collective/cmissearch/i18n/en/LC_MESSAGES/collective.cmissearch.po
src/collective/cmissearch/i18n/fr/LC_MESSAGES/collective.cmissearch.mo
src/collective/cmissearch/i18n/fr/LC_MESSAGES/collective.cmissearch.po
src/collective/cmissearch/i18n/nl/LC_MESSAGES/collective.cmissearch.mo
src/collective/cmissearch/i18n/nl/LC_MESSAGES/collective.cmissearch.po
src/collective/cmissearch/profiles/default/actions.xml
src/collective/cmissearch/profiles/default/portlets.xml
src/collective/cmissearch/templates/searchpage.pt
src/collective/cmissearch/templates/searchportlet.pt
src/collective/cmissearch/templates/simplesearchpage.pt