Metadata-Version: 1.1
Name: collective.cmissearch
Version: 1.0
Summary: CMIS search for Plone
Home-page: http://pypi.python.org/pypi/collective.cmissearch
Author: Sylvain Viollon
Author-email: sylvain@infrae.com
License: GPL
Keywords: CMIS connection search plone
Platform: UNKNOWN
Classifier: Framework :: Plone
Classifier: Framework :: Zope2
